calmatuc/__init__.py
calmatuc/calmatuc.py
calmatuc/instructions.html
calmatuc-0.1.0.dist-info/LICENSE
calmatuc-0.1.0.dist-info/METADATA
calmatuc-0.1.0.dist-info/WHEEL
calmatuc-0.1.0.dist-info/top_level.txt
calmatuc-0.1.0.dist-info/RECORD
